pycyphal/__init__.py
pycyphal/_version.py
pycyphal/py.typed
pycyphal/application/__init__.py
pycyphal/application/_node.py
pycyphal/application/_node_factory.py
pycyphal/application/_port_list_publisher.py
pycyphal/application/_register_server.py
pycyphal/application/_registry_factory.py
pycyphal/application/_transport_factory.py
pycyphal/application/diagnostic.py
pycyphal/application/file.py
pycyphal/application/heartbeat_publisher.py
pycyphal/application/node_tracker.py
pycyphal/application/plug_and_play.py
pycyphal/application/register/__init__.py
pycyphal/application/register/_registry.py
pycyphal/application/register/_value.py
pycyphal/application/register/backend/__init__.py
pycyphal/application/register/backend/dynamic.py
pycyphal/application/register/backend/static.py
pycyphal/dsdl/__init__.py
pycyphal/dsdl/_compiler.py
pycyphal/dsdl/_import_hook.py
pycyphal/dsdl/_lockfile.py
pycyphal/dsdl/_support_wrappers.py
pycyphal/presentation/__init__.py
pycyphal/presentation/_presentation.py
pycyphal/presentation/_port/__init__.py
pycyphal/presentation/_port/_base.py
pycyphal/presentation/_port/_client.py
pycyphal/presentation/_port/_error.py
pycyphal/presentation/_port/_publisher.py
pycyphal/presentation/_port/_server.py
pycyphal/presentation/_port/_subscriber.py
pycyphal/presentation/subscription_synchronizer/__init__.py
pycyphal/presentation/subscription_synchronizer/_common.py
pycyphal/presentation/subscription_synchronizer/monotonic_clustering.py
pycyphal/presentation/subscription_synchronizer/transfer_id.py
pycyphal/transport/__init__.py
pycyphal/transport/_data_specifier.py
pycyphal/transport/_error.py
pycyphal/transport/_payload_metadata.py
pycyphal/transport/_session.py
pycyphal/transport/_timestamp.py
pycyphal/transport/_tracer.py
pycyphal/transport/_transfer.py
pycyphal/transport/_transport.py
pycyphal/transport/can/__init__.py
pycyphal/transport/can/_can.py
pycyphal/transport/can/_frame.py
pycyphal/transport/can/_identifier.py
pycyphal-1.24.2.dist-info/licenses/LICENSE
pycyphal-1.24.2.dist-info/METADATA
pycyphal-1.24.2.dist-info/WHEEL
pycyphal-1.24.2.dist-info/entry_points.txt
pycyphal-1.24.2.dist-info/top_level.txt
pycyphal-1.24.2.dist-info/RECORD
