Metadata-Version: 2.4
Name: pycyphal
Version: 1.24.2
Summary: A full-featured implementation of the Cyphal protocol stack in Python.
Home-page: https://opencyphal.org
Author: OpenCyphal
Author-email: consortium@opencyphal.org
License: MIT
Keywords: cyphal,opencyphal,uavcan,pub-sub,publish-subscribe,data-bus,can-bus,ethernet,vehicular,onboard-networking,avionics,communication-protocol,broker
Classifier: Intended Audience :: Developers
Classifier: Topic :: Scientific/Engineering
Classifier: Topic :: Software Development :: Embedded Systems
Classifier: Topic :: Software Development :: Libraries :: Python Modules
Classifier: Topic :: Software Development :: Object Brokering
Classifier: Topic :: System :: Distributed Computing
Classifier: Topic :: System :: Networking
Classifier: License :: OSI Approved :: MIT License
Classifier: Programming Language :: Python
Classifier: Programming Language :: Python :: 3
Classifier: Operating System :: OS Independent
Classifier: Typing :: Typed
License-File: LICENSE
Requires-Dist: nunavut~=2.3
Requires-Dist: numpy~=2.2
Provides-Extra: transport-can-pythoncan
Requires-Dist: python-can[serial]~=4.0; extra == "transport-can-pythoncan"
Provides-Extra: transport-serial
Requires-Dist: pyserial~=3.5; extra == "transport-serial"
Requires-Dist: cobs~=1.1.4; extra == "transport-serial"
Provides-Extra: transport-udp
Requires-Dist: libpcap<2.0.0,>=0.0.0b0; extra == "transport-udp"
Dynamic: license-file
